{
  "project_info": {
    "project_number": "103332777917",
    "project_id": "geekschat-79965",
    "storage_bucket": "geekschat-79965.appspot.com"
  },
  "client": [
    {
      "client_info": {
        "mobilesdk_app_id": "1:103332777917:android:53a7ace5f1723522e44cd4",
        "android_client_info": {
          "package_name": "com.prosper.geekschat"
        }
      },
      "oauth_client": [],
      "api_key": [
        {
          "current_key": "AIzaSyDThP5orTFa_r3B4v19tc_9nqET27N7C6c"
        }
      ],
      "services": {
        "appinvite_service": {
          "other_platform_oauth_client": []
        }
      }
    }
  ],
  "configuration_version": "1"
}