{
  "project_info": {
    "project_number": "232022304156",
    "project_id": "geekschat-af418",
    "storage_bucket": "geekschat-af418.appspot.com"
  },
  "client": [
    {
      "client_info": {
        "mobilesdk_app_id": "1:232022304156:android:d2566388b6ddedc0dfd459",
        "android_client_info": {
          "package_name": "com.prosper.geekschat"
        }
      },
      "oauth_client": [],
      "api_key": [
        {
          "current_key": "AIzaSyCaqoJAmyTMhgM1IY2Aw4Dri4VpurrtVOQ"
        }
      ],
      "services": {
        "appinvite_service": {
          "other_platform_oauth_client": []
        }
      }
    }
  ],
  "configuration_version": "1"
}